{
  "packageName": "gitvault",
  "packageVersion": "0.2.29",
  "filesScanned": 46,
  "entries": [
    {
      "path": "src/aws_config.rs",
      "publicFunctions": [
        "build_client"
      ],
      "publicTypes": [
        "AwsConfig"
      ],
      "publicConstants": [
        "fn"
      ]
    },
    {
      "path": "src/barrier.rs",
      "publicFunctions": [
        "allow_prod",
        "check_prod_barrier",
        "revoke_prod"
      ],
      "publicTypes": [],
      "publicConstants": []
    },
    {
      "path": "src/cli.rs",
      "publicFunctions": [],
      "publicTypes": [
        "AiAction",
        "AiPrintAction",
        "Cli",
        "Commands",
        "IdentityAction",
        "IdentityProfile",
        "KeyringAction",
        "RecipientAction",
        "SsmAction"
      ],
      "publicConstants": [
        "OUTPUT_KEEP_PATH_SENTINEL"
      ]
    },
    {
      "path": "src/commands/admin.rs",
      "publicFunctions": [
        "cmd_allow_prod",
        "cmd_check",
        "cmd_harden",
        "cmd_merge_driver",
        "cmd_revoke_prod",
        "cmd_status"
      ],
      "publicTypes": [],
      "publicConstants": []
    },
    {
      "path": "src/commands/ai.rs",
      "publicFunctions": [
        "cmd_ai"
      ],
      "publicTypes": [],
      "publicConstants": []
    },
    {
      "path": "src/commands/decrypt.rs",
      "publicFunctions": [
        "cmd_decrypt"
      ],
      "publicTypes": [
        "DecryptOptions"
      ],
      "publicConstants": []
    },
    {
      "path": "src/commands/effects.rs",
      "publicFunctions": [
        "execute_effects",
        "execute_effects_with",
        "new",
        "with_selector"
      ],
      "publicTypes": [
        "CommandOutcome",
        "DefaultRunner",
        "EffectRunner"
      ],
      "publicConstants": []
    },
    {
      "path": "src/commands/encrypt.rs",
      "publicFunctions": [
        "cmd_encrypt"
      ],
      "publicTypes": [],
      "publicConstants": []
    },
    {
      "path": "src/commands/identity.rs",
      "publicFunctions": [
        "cmd_identity",
        "cmd_identity_create"
      ],
      "publicTypes": [],
      "publicConstants": []
    },
    {
      "path": "src/commands/keyring.rs",
      "publicFunctions": [
        "cmd_keyring",
        "cmd_keyring_with_ops"
      ],
      "publicTypes": [],
      "publicConstants": []
    },
    {
      "path": "src/commands/materialize.rs",
      "publicFunctions": [
        "cmd_materialize"
      ],
      "publicTypes": [],
      "publicConstants": []
    },
    {
      "path": "src/commands/mod.rs",
      "publicFunctions": [],
      "publicTypes": [],
      "publicConstants": []
    },
    {
      "path": "src/commands/recipients.rs",
      "publicFunctions": [
        "cmd_recipient",
        "cmd_rotate"
      ],
      "publicTypes": [],
      "publicConstants": []
    },
    {
      "path": "src/commands/run_cmd.rs",
      "publicFunctions": [
        "cmd_run"
      ],
      "publicTypes": [
        "RunOptions"
      ],
      "publicConstants": []
    },
    {
      "path": "src/commands/test_helpers.rs",
      "publicFunctions": [
        "enter",
        "global_test_lock",
        "init_git_repo",
        "lock",
        "setup_identity_file",
        "with_env_var",
        "with_identity_env",
        "write_encrypted_env_file"
      ],
      "publicTypes": [
        "CwdGuard",
        "GlobalTestMutex"
      ],
      "publicConstants": []
    },
    {
      "path": "src/config.rs",
      "publicFunctions": [
        "account",
        "default_env",
        "effective_config",
        "env_file",
        "load_config",
        "load_global_config",
        "materialize_output",
        "prod_name",
        "recipients_file",
        "service",
        "ttl_secs"
      ],
      "publicTypes": [
        "BarrierConfig",
        "EnvConfig",
        "GitvaultConfig",
        "HookAdapter",
        "HooksConfig",
        "KeyringConfig",
        "PathsConfig"
      ],
      "publicConstants": [
        "fn"
      ]
    },
    {
      "path": "src/crypto.rs",
      "publicFunctions": [
        "as_identity",
        "decrypt",
        "decrypt_stream",
        "encrypt",
        "encrypt_stream",
        "parse_identity",
        "parse_identity_any",
        "parse_recipient"
      ],
      "publicTypes": [
        "AnyIdentity"
      ],
      "publicConstants": [
        "GITVAULT_FORMAT_VERSION"
      ]
    },
    {
      "path": "src/defaults.rs",
      "publicFunctions": [],
      "publicTypes": [],
      "publicConstants": [
        "BARRIER_TOKEN_FILE",
        "DEFAULT_BARRIER_TTL_SECS",
        "DEFAULT_ENV",
        "DEFAULT_PROD_ENV",
        "ENV_FILE",
        "KEYRING_ACCOUNT",
        "KEYRING_SERVICE",
        "MATERIALIZE_OUTPUT",
        "PLAIN_BASE_DIR",
        "RECIPIENTS_FILE",
        "SECRETS_DIR"
      ]
    },
    {
      "path": "src/dispatch.rs",
      "publicFunctions": [
        "run"
      ],
      "publicTypes": [],
      "publicConstants": []
    },
    {
      "path": "src/env.rs",
      "publicFunctions": [
        "resolve_env",
        "validate_env_name"
      ],
      "publicTypes": [],
      "publicConstants": []
    },
    {
      "path": "src/error.rs",
      "publicFunctions": [],
      "publicTypes": [
        "GitvaultError"
      ],
      "publicConstants": [
        "EXIT_BARRIER",
        "EXIT_DECRYPT_ERROR",
        "EXIT_DRIFT",
        "EXIT_ERROR",
        "EXIT_PLAINTEXT_LEAK",
        "EXIT_SUCCESS",
        "EXIT_USAGE",
        "fn"
      ]
    },
    {
      "path": "src/fhsm.rs",
      "publicFunctions": [
        "resolve_identity_source",
        "transition"
      ],
      "publicTypes": [
        "Effect",
        "Event",
        "FhsmError",
        "IdentitySource"
      ],
      "publicConstants": []
    },
    {
      "path": "src/identity.rs",
      "publicFunctions": [
        "extract_identity_key",
        "list_ssh_agent_keys",
        "load_identity",
        "load_identity_from_source",
        "load_identity_from_source_with_selector",
        "load_identity_source",
        "load_identity_with",
        "load_identity_with_selector",
        "probe_identity_sources",
        "resolve_recipient_keys"
      ],
      "publicTypes": [
        "IdentitySourceState",
        "SshAgentError",
        "SshAgentKey"
      ],
      "publicConstants": []
    },
    {
      "path": "src/keyring_store.rs",
      "publicFunctions": [
        "keyring_delete",
        "keyring_delete_with",
        "keyring_get",
        "keyring_get_with",
        "keyring_set",
        "keyring_set_with"
      ],
      "publicTypes": [],
      "publicConstants": []
    },
    {
      "path": "src/lib.rs",
      "publicFunctions": [],
      "publicTypes": [],
      "publicConstants": []
    },
    {
      "path": "src/main.rs",
      "publicFunctions": [],
      "publicTypes": [],
      "publicConstants": []
    },
    {
      "path": "src/materialize.rs",
      "publicFunctions": [
        "ensure_gitattributes",
        "ensure_gitignored",
        "materialize_env_file"
      ],
      "publicTypes": [],
      "publicConstants": [
        "GITATTRIBUTES_MERGE_DRIVER_ENTRY",
        "REQUIRED_GITIGNORE_ENTRIES"
      ]
    },
    {
      "path": "src/merge.rs",
      "publicFunctions": [
        "merge_env_content",
        "parse_env_key_from_line",
        "parse_env_pair_from_line",
        "parse_env_pairs",
        "rewrite_env_assignment_line"
      ],
      "publicTypes": [],
      "publicConstants": []
    },
    {
      "path": "src/output.rs",
      "publicFunctions": [
        "ci_is_non_interactive",
        "output_success",
        "resolve_no_prompt"
      ],
      "publicTypes": [],
      "publicConstants": []
    },
    {
      "path": "src/permissions.rs",
      "publicFunctions": [
        "enforce_owner_rw",
        "enforce_windows_acl_with"
      ],
      "publicTypes": [],
      "publicConstants": []
    },
    {
      "path": "src/repo/drift.rs",
      "publicFunctions": [
        "check_no_tracked_plaintext",
        "has_secrets_drift"
      ],
      "publicTypes": [],
      "publicConstants": []
    },
    {
      "path": "src/repo/hooks.rs",
      "publicFunctions": [
        "install_git_hooks",
        "resolve_hooks_dir"
      ],
      "publicTypes": [],
      "publicConstants": []
    },
    {
      "path": "src/repo/mod.rs",
      "publicFunctions": [],
      "publicTypes": [],
      "publicConstants": []
    },
    {
      "path": "src/repo/paths.rs",
      "publicFunctions": [
        "decrypt_env_secrets",
        "ensure_dirs",
        "find_repo_root",
        "find_repo_root_from",
        "get_encrypted_path",
        "get_env_encrypted_dir",
        "get_env_encrypted_path",
        "get_plain_path",
        "list_all_encrypted_files",
        "list_encrypted_files_for_env",
        "validate_write_path"
      ],
      "publicTypes": [],
      "publicConstants": []
    },
    {
      "path": "src/repo/plugin.rs",
      "publicFunctions": [
        "find_adapter_binary",
        "invoke_adapter_harden"
      ],
      "publicTypes": [
        "AdapterLookup"
      ],
      "publicConstants": []
    },
    {
      "path": "src/repo/recipients.rs",
      "publicFunctions": [
        "read_recipients",
        "write_recipients"
      ],
      "publicTypes": [],
      "publicConstants": []
    },
    {
      "path": "src/run.rs",
      "publicFunctions": [
        "run_command"
      ],
      "publicTypes": [],
      "publicConstants": []
    },
    {
      "path": "src/ssm/backend.rs",
      "publicFunctions": [],
      "publicTypes": [
        "RealSsmBackend",
        "SsmBackend"
      ],
      "publicConstants": []
    },
    {
      "path": "src/ssm/commands.rs",
      "publicFunctions": [
        "cmd_ssm_diff",
        "cmd_ssm_diff_with",
        "cmd_ssm_pull",
        "cmd_ssm_pull_with",
        "cmd_ssm_push",
        "cmd_ssm_push_with",
        "cmd_ssm_set",
        "cmd_ssm_set_with"
      ],
      "publicTypes": [],
      "publicConstants": []
    },
    {
      "path": "src/ssm/mod.rs",
      "publicFunctions": [],
      "publicTypes": [],
      "publicConstants": []
    },
    {
      "path": "src/ssm/refs.rs",
      "publicFunctions": [
        "get_app_name",
        "load_refs",
        "refs_file_path",
        "save_refs",
        "ssm_path",
        "validate_app_name"
      ],
      "publicTypes": [],
      "publicConstants": []
    },
    {
      "path": "src/structured/armor.rs",
      "publicFunctions": [
        "decrypt_armor",
        "decrypt_binary_b64",
        "encrypt_armor",
        "encrypt_binary_b64"
      ],
      "publicTypes": [],
      "publicConstants": []
    },
    {
      "path": "src/structured/env_values.rs",
      "publicFunctions": [
        "decrypt_env_values",
        "encrypt_env_values"
      ],
      "publicTypes": [],
      "publicConstants": []
    },
    {
      "path": "src/structured/fields.rs",
      "publicFunctions": [
        "decrypt_fields",
        "encrypt_fields"
      ],
      "publicTypes": [],
      "publicConstants": []
    },
    {
      "path": "src/structured/helpers.rs",
      "publicFunctions": [
        "atomic_write",
        "is_age_armor",
        "is_env_encrypted"
      ],
      "publicTypes": [],
      "publicConstants": [
        "AGE_ARMOR_HEADER",
        "ENV_ENC_PREFIX"
      ]
    },
    {
      "path": "src/structured/mod.rs",
      "publicFunctions": [],
      "publicTypes": [],
      "publicConstants": []
    }
  ]
}
